helloworld.py
helloworld_vinayak-0.0.0.dist-info/LICENSE.txt
helloworld_vinayak-0.0.0.dist-info/METADATA
helloworld_vinayak-0.0.0.dist-info/WHEEL
helloworld_vinayak-0.0.0.dist-info/top_level.txt
helloworld_vinayak-0.0.0.dist-info/RECORD
